syncticketstoclickup/__init__.py
syncticketstoclickup/clickup.py
syncticketstoclickup/main.py
syncticketstoclickup/zendesk.py
syncticketstoclickup/zendesk_to_clickup.py
syncticketstoclickup-1.0.3.dist-info/LICENSE
syncticketstoclickup-1.0.3.dist-info/METADATA
syncticketstoclickup-1.0.3.dist-info/WHEEL
syncticketstoclickup-1.0.3.dist-info/top_level.txt
syncticketstoclickup-1.0.3.dist-info/RECORD
