Metadata-Version: 2.1
Name: syncticketstoclickup
Version: 1.0.3
Summary: A package that allows to sync tickets from Zendesk to ClickUp.
Author: abrahamprz (Abraham Perez)
Author-email: fcoabrahamprz@gmail.com
Keywords: python,zendesk,clickup,ticket,task,sync,requests
Classifier: Development Status :: 1 - Planning
Classifier: Intended Audience :: Developers
Classifier: Programming Language :: Python :: 3.10
Classifier: Operating System :: Unix
Classifier: License :: OSI Approved :: MIT License
License-File: LICENSE
Requires-Dist: requests
Requires-Dist: tqdm
Requires-Dist: python-dotenv
